{"pushed_at":"2026-06-29T15:26:46","scanner_status":"online","dashboard":{"tahap0":0,"tahap1":161,"tahap2":0,"tahap3":14,"sinyal_dikirim":9,"sinyal_masih_valid":2,"sinyal_sudah_exit":7,"sinyal_expired":0,"gagal":35,"universe_count":219,"stocks_tahap0":[],"stocks_tahap1":["AADI","ACES","ADHI","ADMR","ADRO","AKRA","AMMN","AMRT","ANTM","APIC","ARCI","ARTO","ASII","ASLC","ASLI","ASSA","AVIA","AYAM","BBCA","BBKP","BBNI","BBRI","BBYB","BEEF","BFIN","BIPI","BKSL","BMRI","BNGA","BREN","BRIS","BRMS","BRPT","BSDE","BTPS","BULL","BUMI","BUVA","CARE","CASA","CBDK","CBRE","CDIA","CLEO","CMNT","CMRY","COCO","COIN","CTRA","CTTH","CUAN","CYBR","DAAZ","DATA","DEWA","DKFT","DOOH","EMAS","ENRG","ERAA","ESSA","EXCL","FORE","FPNI","FUTR","GGRM","GMFI","GPRA","GTSI","GZCO","HEAL","HRTA","HUMI","IATA","IKAN","IMJS","IMPC","INCO","INDF","INET","INKP","INTP","IRSX","ISAT","JGLE","JPFA","JSMR","KBLV","KETR","KIJA","KLBF","KPIG","KRAS","KRYA","LABA","MAPA","MAPI","MARK","MBMA","MBSS","MDKA","MEDC","MEJA","MERI","MGRO","MIKA","MINA","MLPL","MSIN","MTEL","NCKL","NICL","NRCA","NTBK","OASA","PADA","PANI","PGAS","PGEO","PIPA","PJHB","PSAB","PSKT","PTBA","PTPP","PTRO","PWON","PYFA","RAJA","RATU","REAL","RLCO","RMKE","SCMA","SGRO","SIDO","SLIS","SMBR","SMIL","SMRA","SOLA","SRTG","SSIA","SSMS","STAA","TAPG","TCPI","TINS","TKIM","TLKM","TOBA","TOSK","TOWR","TPIA","TRUE","UNIQ","VKTR","WIFI","WIRG","WOWS","YELO"],"stocks_tahap2":[],"stocks_tahap3":["BUKA","DSNG","DSSA","ELSA","EMTK","FILM","HRUM","ICBP","MYOR","PADI","PPRI","RISE","SGER","SMDR"],"stocks_sinyal_valid":["FAST","UANG"],"stocks_sinyal_exit":["BWPT","HALO","LAPD","OBAT","PNLF","SUPA","SURI"],"stocks_sinyal_expired":[],"stocks_gagal":["AALI","BBTN","BEKS","BLOG","BSBK","CARS","CNKO","COAL","CPIN","CPRO","DADA","ELTY","GOTO","HATM","HDIT","HILL","HMSP","INDY","ITMG","JARR","KARW","MTFN","PBRX","PNBN","SINI","SMGR","SRAJ","TEBE","TRIN","UNTR","UNVR","WIIM","WMUU","WSBP","ZATA"]},"signals_valid":[{"stock_code":"UANG","status":"entered","tick_to_entry":0,"entry_price":2040,"sl_price":2000,"tp_price":2080,"time_stop":"15:45","per_user_lots":[{"user_id":2014518935,"lot":146,"profit":463404,"loss":-701676},{"user_id":8932299477,"lot":27,"profit":85698,"loss":-129762},{"user_id":1341444291,"lot":14,"profit":44436,"loss":-67284},{"user_id":8929207795,"lot":14,"profit":44436,"loss":-67284},{"user_id":6633029014,"lot":14,"profit":44436,"loss":-67284},{"user_id":7601109564,"lot":10,"profit":31740,"loss":-48060},{"user_id":5537656752,"lot":8,"profit":25392,"loss":-38448},{"user_id":8286695873,"lot":7,"profit":22218,"loss":-33642},{"user_id":1232047915,"lot":7,"profit":22218,"loss":-33642},{"user_id":7648694610,"lot":7,"profit":22218,"loss":-33642},{"user_id":5154932253,"lot":1,"profit":3174,"loss":-4806}]},{"stock_code":"FAST","status":"entered","tick_to_entry":-1,"entry_price":212,"sl_price":208,"tp_price":216,"time_stop":"15:45","per_user_lots":[{"user_id":2014518935,"lot":1412,"profit":443650,"loss":-683125},{"user_id":8932299477,"lot":261,"profit":82006,"loss":-126271},{"user_id":1341444291,"lot":141,"profit":44302,"loss":-68215},{"user_id":8929207795,"lot":141,"profit":44302,"loss":-68215},{"user_id":6633029014,"lot":141,"profit":44302,"loss":-68215},{"user_id":7601109564,"lot":98,"profit":30791,"loss":-47412},{"user_id":5537656752,"lot":81,"profit":25450,"loss":-39187},{"user_id":8286695873,"lot":70,"profit":21994,"loss":-33866},{"user_id":1232047915,"lot":70,"profit":21994,"loss":-33866},{"user_id":7648694610,"lot":69,"profit":21679,"loss":-33382},{"user_id":5154932253,"lot":10,"profit":3142,"loss":-4838}]}],"signals_exited":[{"stock_code":"PNLF","exit_type":"TP","exit_time":"15:26","entry_price":220,"sl_price":216,"tp_price":224,"per_user_lots":[{"user_id":2014518935,"lot":1361,"profit":423271,"loss":-662807},{"user_id":8932299477,"lot":252,"profit":78372,"loss":-122724},{"user_id":1341444291,"lot":136,"profit":42296,"loss":-66232},{"user_id":8929207795,"lot":136,"profit":42296,"loss":-66232},{"user_id":6633029014,"lot":136,"profit":42296,"loss":-66232},{"user_id":7601109564,"lot":95,"profit":29545,"loss":-46265},{"user_id":5537656752,"lot":78,"profit":24258,"loss":-37986},{"user_id":8286695873,"lot":68,"profit":21148,"loss":-33116},{"user_id":1232047915,"lot":68,"profit":21148,"loss":-33116},{"user_id":7648694610,"lot":67,"profit":20837,"loss":-32629},{"user_id":5154932253,"lot":9,"profit":2799,"loss":-4383}]},{"stock_code":"OBAT","exit_type":"TP","exit_time":"15:26","entry_price":234,"sl_price":230,"tp_price":238,"per_user_lots":[{"user_id":2014518935,"lot":1280,"profit":390912,"loss":-630528},{"user_id":8932299477,"lot":237,"profit":72379,"loss":-116746},{"user_id":1341444291,"lot":128,"profit":39091,"loss":-63052},{"user_id":8929207795,"lot":128,"profit":39091,"loss":-63052},{"user_id":6633029014,"lot":128,"profit":39091,"loss":-63052},{"user_id":7601109564,"lot":89,"profit":27180,"loss":-43841},{"user_id":5537656752,"lot":74,"profit":22599,"loss":-36452},{"user_id":8286695873,"lot":64,"profit":19545,"loss":-31526},{"user_id":1232047915,"lot":64,"profit":19545,"loss":-31526},{"user_id":7648694610,"lot":63,"profit":19240,"loss":-31033},{"user_id":5154932253,"lot":9,"profit":2748,"loss":-4433}]},{"stock_code":"LAPD","exit_type":"TP","exit_time":"15:26","entry_price":55,"sl_price":53,"tp_price":57,"per_user_lots":[{"user_id":2014518935,"lot":4992,"profit":886080,"loss":-1105728},{"user_id":8932299477,"lot":924,"profit":164010,"loss":-204666},{"user_id":1341444291,"lot":499,"profit":88572,"loss":-110528},{"user_id":8929207795,"lot":499,"profit":88572,"loss":-110528},{"user_id":6633029014,"lot":499,"profit":88572,"loss":-110528},{"user_id":7601109564,"lot":349,"profit":61947,"loss":-77303},{"user_id":5537656752,"lot":289,"profit":51297,"loss":-64013},{"user_id":8286695873,"lot":249,"profit":44197,"loss":-55153},{"user_id":1232047915,"lot":249,"profit":44197,"loss":-55153},{"user_id":7648694610,"lot":246,"profit":43665,"loss":-54489},{"user_id":5154932253,"lot":35,"profit":6212,"loss":-7752}]},{"stock_code":"SUPA","exit_type":"TP","exit_time":"15:26","entry_price":535,"sl_price":525,"tp_price":545,"per_user_lots":[{"user_id":2014518935,"lot":559,"profit":437976,"loss":-677228},{"user_id":8932299477,"lot":103,"profit":80700,"loss":-124784},{"user_id":1341444291,"lot":55,"profit":43092,"loss":-66632},{"user_id":8929207795,"lot":55,"profit":43092,"loss":-66632},{"user_id":6633029014,"lot":55,"profit":43092,"loss":-66632},{"user_id":7601109564,"lot":39,"profit":30556,"loss":-47248},{"user_id":5537656752,"lot":32,"profit":25072,"loss":-38768},{"user_id":8286695873,"lot":27,"profit":21154,"loss":-32710},{"user_id":1232047915,"lot":27,"profit":21154,"loss":-32710},{"user_id":7648694610,"lot":27,"profit":21154,"loss":-32710},{"user_id":5154932253,"lot":3,"profit":2350,"loss":-3634}]},{"stock_code":"SURI","exit_type":"TP","exit_time":"15:26","entry_price":60,"sl_price":58,"tp_price":62,"per_user_lots":[{"user_id":2014518935,"lot":4992,"profit":876096,"loss":-1115712},{"user_id":8932299477,"lot":924,"profit":162162,"loss":-206514},{"user_id":1341444291,"lot":499,"profit":87574,"loss":-111526},{"user_id":8929207795,"lot":499,"profit":87574,"loss":-111526},{"user_id":6633029014,"lot":499,"profit":87574,"loss":-111526},{"user_id":7601109564,"lot":349,"profit":61249,"loss":-78001},{"user_id":5537656752,"lot":289,"profit":50719,"loss":-64591},{"user_id":8286695873,"lot":249,"profit":43699,"loss":-55651},{"user_id":1232047915,"lot":249,"profit":43699,"loss":-55651},{"user_id":7648694610,"lot":246,"profit":43173,"loss":-54981},{"user_id":5154932253,"lot":35,"profit":6142,"loss":-7822}]},{"stock_code":"HALO","exit_type":"TP","exit_time":"15:26","entry_price":59,"sl_price":57,"tp_price":61,"per_user_lots":[{"user_id":2014518935,"lot":4992,"profit":878092,"loss":-1113715},{"user_id":8932299477,"lot":924,"profit":162531,"loss":-206144},{"user_id":1341444291,"lot":499,"profit":87774,"loss":-111326},{"user_id":8929207795,"lot":499,"profit":87774,"loss":-111326},{"user_id":6633029014,"lot":499,"profit":87774,"loss":-111326},{"user_id":7601109564,"lot":349,"profit":61389,"loss":-77861},{"user_id":5537656752,"lot":289,"profit":50835,"loss":-64475},{"user_id":8286695873,"lot":249,"profit":43799,"loss":-55551},{"user_id":1232047915,"lot":249,"profit":43799,"loss":-55551},{"user_id":7648694610,"lot":246,"profit":43271,"loss":-54882},{"user_id":5154932253,"lot":35,"profit":6156,"loss":-7808}]},{"stock_code":"BWPT","exit_type":"TP","exit_time":"15:26","entry_price":75,"sl_price":73,"tp_price":77,"per_user_lots":[{"user_id":2014518935,"lot":3994,"profit":676983,"loss":-916623},{"user_id":8932299477,"lot":739,"profit":125260,"loss":-169600},{"user_id":1341444291,"lot":399,"profit":67630,"loss":-91570},{"user_id":8929207795,"lot":399,"profit":67630,"loss":-91570},{"user_id":6633029014,"lot":399,"profit":67630,"loss":-91570},{"user_id":7601109564,"lot":279,"profit":47290,"loss":-64030},{"user_id":5537656752,"lot":231,"profit":39154,"loss":-53014},{"user_id":8286695873,"lot":199,"profit":33730,"loss":-45670},{"user_id":1232047915,"lot":199,"profit":33730,"loss":-45670},{"user_id":7648694610,"lot":197,"profit":33391,"loss":-45211},{"user_id":5154932253,"lot":28,"profit":4746,"loss":-6426}]}],"universe":["AADI","AALI","ACES","ADHI","ADMR","ADRO","AKRA","AMMN","AMRT","ANTM","APIC","ARCI","ARTO","ASII","ASLC","ASLI","ASSA","AVIA","AYAM","BBCA","BBKP","BBNI","BBRI","BBTN","BBYB","BEEF","BEKS","BFIN","BIPI","BKSL","BLOG","BMRI","BNGA","BREN","BRIS","BRMS","BRPT","BSBK","BSDE","BTPS","BUKA","BULL","BUMI","BUVA","BWPT","CARE","CARS","CASA","CBDK","CBRE","CDIA","CLEO","CMNT","CMRY","CNKO","COAL","COCO","COIN","CPIN","CPRO","CTRA","CTTH","CUAN","CYBR","DAAZ","DADA","DATA","DEWA","DKFT","DOOH","DSNG","DSSA","ELSA","ELTY","EMAS","EMTK","ENRG","ERAA","ESSA","EXCL","FAST","FILM","FORE","FPNI","FUTR","GGRM","GMFI","GOTO","GPRA","GTSI","GZCO","HALO","HATM","HDIT","HEAL","HILL","HMSP","HRTA","HRUM","HUMI","IATA","ICBP","IKAN","IMJS","IMPC","INCO","INDF","INDY","INET","INKP","INTP","IRSX","ISAT","ITMG","JARR","JGLE","JPFA","JSMR","KARW","KBLV","KETR","KIJA","KLBF","KPIG","KRAS","KRYA","LABA","LAPD","MAPA","MAPI","MARK","MBMA","MBSS","MDKA","MEDC","MEJA","MERI","MGRO","MIKA","MINA","MLPL","MSIN","MTEL","MTFN","MYOR","NCKL","NICL","NRCA","NTBK","OASA","OBAT","PADA","PADI","PANI","PBRX","PGAS","PGEO","PIPA","PJHB","PNBN","PNLF","PPRI","PSAB","PSKT","PTBA","PTPP","PTRO","PWON","PYFA","RAJA","RATU","REAL","RISE","RLCO","RMKE","SCMA","SGER","SGRO","SIDO","SINI","SLIS","SMBR","SMDR","SMGR","SMIL","SMRA","SOLA","SRAJ","SRTG","SSIA","SSMS","STAA","SUPA","SURI","TAPG","TCPI","TEBE","TINS","TKIM","TLKM","TOBA","TOSK","TOWR","TPIA","TRIN","TRUE","UANG","UNIQ","UNTR","UNVR","VKTR","WIFI","WIIM","WIRG","WMUU","WOWS","WSBP","YELO","ZATA"]}